ctisearch/__init__.py
ctisearch/base.py
ctisearch/shodan.py
ctisearch/urlscan.py
ctisearch/virustotal.py
ctisearch-0.0.3.dist-info/METADATA
ctisearch-0.0.3.dist-info/WHEEL
ctisearch-0.0.3.dist-info/licenses/LICENSE
ctisearch-0.0.3.dist-info/RECORD
