Metadata-Version: 2.3
Name: ctisearch
Version: 0.0.3
Summary: A broadly common async interface for Shodan, URLScan, and VirusTotal
Project-URL: Homepage, https://github.com/kmsec-uk/ctisearch
Project-URL: Issues, https://github.com/kmsec-uk/ctisearch/issues
Author-email: kmsec-uk <kmsec-uk@proton.me>
License-File: LICENSE
Classifier: License :: OSI Approved :: MIT License
Classifier: Operating System :: OS Independent
Classifier: Programming Language :: Python :: 3
Requires-Python: >=3.11
Requires-Dist: aiohttp==3.10.8
Requires-Dist: vt-py==0.18.4
